breba_docs/__init__.py
breba_docs/agent/__init__.py
breba_docs/agent/agent.py
breba_docs/agent/command_exec_agent.py
breba_docs/agent/graph_agent.py
breba_docs/agent/instruction_reader.py
breba_docs/agent/instructions/analyze_output.jinja2
breba_docs/agent/instructions/fetch_commands.jinja2
breba_docs/agent/instructions/fetch_modify_file_commands.jinja2
breba_docs/agent/instructions/fetch_modify_file_commands_message_1.jinja2
breba_docs/agent/instructions/identify_goals.jinja2
breba_docs/agent/instructions/provide_input_1.jinja2
breba_docs/agent/instructions/provide_input_2.jinja2
breba_docs/agent/instructions/reactive_analyze_output.jinja2
breba_docs/agent/openai_agent.py
breba_docs/analyzer/__init__.py
breba_docs/analyzer/document_analyzer.py
breba_docs/analyzer/reporter.py
breba_docs/cli/__init__.py
breba_docs/cli/app.py
breba_docs/cli/commands/__init_.py
breba_docs/cli/commands/new_command.py
breba_docs/cli/commands/run_command.py
breba_docs/config.py
breba_docs/container.py
breba_docs/services/__init__.py
breba_docs/services/command_executor.py
breba_docs/services/document.py
breba_docs/services/reports.py
breba_docs-0.4.0.dist-info/LICENSE
breba_docs-0.4.0.dist-info/METADATA
breba_docs-0.4.0.dist-info/WHEEL
breba_docs-0.4.0.dist-info/entry_points.txt
breba_docs-0.4.0.dist-info/RECORD
