Metadata-Version: 2.3
Name: breba-docs
Version: 0.4.0
Summary: Documentation assistant will proof read your docs
License: MIT
Keywords: gpt,assistant,documentation
Author: Yason Khaburzaniya
Author-email: yason@hey.com
Requires-Python: >=3.10,<4.0
Classifier: License :: OSI Approved :: MIT License
Classifier: Operating System :: OS Independent
Classifier: Programming Language :: Python :: 3
Classifier: Programming Language :: Python :: 3.10
Classifier: Programming Language :: Python :: 3.11
Classifier: Programming Language :: Python :: 3.12
Classifier: Programming Language :: Python :: 3.13
Requires-Dist: cleo (>=2.1.0,<3.0.0)
Requires-Dist: docker (>=7.1.0,<8.0.0)
Requires-Dist: gitpython (>=3.1.43,<4.0.0)
Requires-Dist: interactive-process (>=0.2.0,<0.3.0)
Requires-Dist: jinja2 (>=3.1.4,<4.0.0)
Requires-Dist: langchain-core (>=0.3.21,<0.4.0)
Requires-Dist: langchain-openai (>=0.2.10,<0.3.0)
Requires-Dist: langgraph (>=0.2.53,<0.3.0)
Requires-Dist: openai (>=1.38.0,<2.0.0)
Requires-Dist: pexpect (>=4.9.0,<5.0.0)
Requires-Dist: pty-server (>=0.1.10,<0.2.0)
Requires-Dist: pytest-asyncio (>=0.25.0,<0.26.0)
Requires-Dist: python-dotenv (>=1.0.1,<2.0.0)
Requires-Dist: requests (>=2.32.3,<3.0.0)
Project-URL: Documentation, https://github.com/breba-apps/breba-docs
Project-URL: Homepage, https://github.com/breba-apps/breba-docs
Project-URL: Repository, https://github.com/breba-apps/breba-docs
